README.md
setup.py
neupy_core_base_assembly_src/Mean.py
neupy_core_base_assembly_src/Median.py
neupy_core_base_assembly_src/Variance.py
neupy_core_base_assembly_src/__init__.py
neupy_core_base_assembly_zrq.egg-info/PKG-INFO
neupy_core_base_assembly_zrq.egg-info/SOURCES.txt
neupy_core_base_assembly_zrq.egg-info/dependency_links.txt
neupy_core_base_assembly_zrq.egg-info/top_level.txt
resources/__init__.py
scripts/__init__.py
src/Mean.py
src/Median.py
src/Variance.py
src/__init__.py